[
  {
    "name": "City, University of London (Royaume-Uni)",
    "country": "Royaume-Uni",
    "full_name": "City, University of London",
    "id": "grid.28577.3f",
    "y": 1,
    "z": 49
  },
  {
    "name": "SERM (France)",
    "country": "France",
    "full_name": "Société Equipement Région Montpelliéraine",
    "acronym": "SERM",
    "id": "462800160",
    "y": 1,
    "z": 1
  },
  {
    "name": "CEA (France)",
    "country": "France",
    "full_name": "Commissariat à l’énergie atomique et aux énergies alternatives",
    "acronym": "CEA",
    "id": "zYXK8",
    "y": 1,
    "z": 852
  },
  {
    "name": "Iznab (Pologne)",
    "country": "Pologne",
    "full_name": "Iznab",
    "id": "grid.436013.3",
    "y": 1,
    "z": 9
  },
  {
    "name": "Centre for Technology Research & Innovation (Chypre)",
    "country": "Chypre",
    "full_name": "Centre for Technology Research & Innovation",
    "id": "grid.423510.1",
    "y": 1,
    "z": 14
  },
  {
    "name": "Centre for Research and Technology Hellas (Grèce)",
    "country": "Grèce",
    "full_name": "Centre for Research and Technology Hellas",
    "id": "grid.423747.1",
    "y": 1,
    "z": 361
  }
]