[
  {
    "name": "Arçelik (Turquie)",
    "country": "Turquie",
    "full_name": "Arçelik",
    "id": "grid.424171.5",
    "y": 1,
    "z": 21
  },
  {
    "name": "Inria (France)",
    "country": "France",
    "full_name": "Institut national de recherche en informatique et en automatique",
    "acronym": "Inria",
    "id": "E1Wdn",
    "y": 1,
    "z": 295
  },
  {
    "name": "EnginSoft (Italie)",
    "country": "Italie",
    "full_name": "EnginSoft",
    "id": "grid.424476.7",
    "y": 1,
    "z": 11
  },
  {
    "name": "IMT Atlantique (France)",
    "country": "France",
    "full_name": "IMT Atlantique Bretagne Pays de la Loire",
    "acronym": "IMT Atlantique",
    "id": "krqUz",
    "y": 1,
    "z": 49
  },
  {
    "name": "Fiat Chrysler Automobiles (Italie)",
    "country": "Italie",
    "full_name": "Fiat Chrysler Automobiles",
    "id": "grid.425176.3",
    "y": 1,
    "z": 41
  },
  {
    "name": "Politecnico di Milano (Italie)",
    "country": "Italie",
    "full_name": "Politecnico di Milano",
    "id": "grid.4643.5",
    "y": 1,
    "z": 386
  },
  {
    "name": "ECN (France)",
    "country": "France",
    "full_name": "Centrale Nantes",
    "acronym": "ECN",
    "id": "gCAyK",
    "y": 1,
    "z": 30
  },
  {
    "name": "U. Nantes (France)",
    "country": "France",
    "full_name": "Université de Nantes",
    "acronym": "U. Nantes",
    "id": "7hB8r",
    "y": 1,
    "z": 71
  },
  {
    "name": "Gizelis Robotics (Grèce)",
    "country": "Grèce",
    "full_name": "Gizelis Robotics",
    "id": "grid.433538.a",
    "y": 1,
    "z": 5
  },
  {
    "name": "University of Patras (Grèce)",
    "country": "Grèce",
    "full_name": "University of Patras",
    "id": "grid.11047.33",
    "y": 1,
    "z": 138
  },
  {
    "name": "Airbus (Allemagne)",
    "country": "Allemagne",
    "full_name": "Airbus",
    "id": "grid.410308.e",
    "y": 1,
    "z": 91
  },
  {
    "name": "CNRS (France)",
    "country": "France",
    "full_name": "Centre national de la recherche scientifique",
    "acronym": "CNRS",
    "id": "n2X5f",
    "y": 1,
    "z": 2670
  },
  {
    "name": "Karlsruhe Institute of Technology (Allemagne)",
    "country": "Allemagne",
    "full_name": "Karlsruhe Institute of Technology",
    "id": "grid.7892.4",
    "y": 1,
    "z": 268
  }
]