{
  "all": {
    "all": [
      {
        "name": "Instituto de Engenharia de Sistemas e Computadores Investigação e Desenvolvimento (Portugal)",
        "country": "Portugal",
        "full_name": "Instituto de Engenharia de Sistemas e Computadores Investigação e Desenvolvimento",
        "id": "grid.14647.30",
        "country_level_part": "Pays membres",
        "y": 1,
        "z": 22
      },
      {
        "name": "Centre Tecnologic De Telecomunicacions De Catalunya (Espagne)",
        "country": "Espagne",
        "full_name": "Centre Tecnologic De Telecomunicacions De Catalunya",
        "id": "grid.28409.37",
        "country_level_part": "Pays membres",
        "y": 1,
        "z": 155
      },
      {
        "name": "University of Žilina (Slovaquie)",
        "country": "Slovaquie",
        "full_name": "University of Žilina",
        "id": "grid.7960.8",
        "country_level_part": "Pays membres",
        "y": 1,
        "z": 16
      },
      {
        "name": "Transportes Inovação e Sistemas (Portugal)",
        "country": "Portugal",
        "full_name": "Transportes Inovação e Sistemas",
        "id": "grid.426229.9",
        "country_level_part": "Pays membres",
        "y": 1,
        "z": 8
      }
    ]
  },
  "Societal Challenges": {
    "Smart, green and integrated transport (TPT)": [
      {
        "name": "Instituto de Engenharia de Sistemas e Computadores Investigação e Desenvolvimento (Portugal)",
        "country": "Portugal",
        "full_name": "Instituto de Engenharia de Sistemas e Computadores Investigação e Desenvolvimento",
        "id": "grid.14647.30",
        "country_level_part": "Pays membres",
        "y": 1,
        "z": 2
      },
      {
        "name": "Centre Tecnologic De Telecomunicacions De Catalunya (Espagne)",
        "country": "Espagne",
        "full_name": "Centre Tecnologic De Telecomunicacions De Catalunya",
        "id": "grid.28409.37",
        "country_level_part": "Pays membres",
        "y": 1,
        "z": 17
      },
      {
        "name": "University of Žilina (Slovaquie)",
        "country": "Slovaquie",
        "full_name": "University of Žilina",
        "id": "grid.7960.8",
        "country_level_part": "Pays membres",
        "y": 1,
        "z": 12
      },
      {
        "name": "Transportes Inovação e Sistemas (Portugal)",
        "country": "Portugal",
        "full_name": "Transportes Inovação e Sistemas",
        "id": "grid.426229.9",
        "country_level_part": "Pays membres",
        "y": 1,
        "z": 7
      }
    ]
  }
}