[
  {
    "name": "CEA (France)",
    "country": "France",
    "full_name": "Commissariat à l’énergie atomique et aux énergies alternatives",
    "acronym": "CEA",
    "id": "zYXK8",
    "y": 4,
    "z": 852
  },
  {
    "name": "Wageningen University & Research (Pays-Bas)",
    "country": "Pays-Bas",
    "full_name": "Wageningen University & Research",
    "id": "grid.4818.5",
    "y": 3,
    "z": 367
  },
  {
    "name": "Institut de l'elevage (France)",
    "country": "France",
    "full_name": "Institut de l'elevage",
    "acronym": "Institut de l'elevage",
    "id": "302984158",
    "y": 2,
    "z": 33
  },
  {
    "name": "Teagasc - The Irish Agriculture and Food Development Authority (Irlande)",
    "country": "Irlande",
    "full_name": "Teagasc - The Irish Agriculture and Food Development Authority",
    "id": "grid.6435.4",
    "y": 2,
    "z": 78
  },
  {
    "name": "University of Debrecen (Hongrie)",
    "country": "Hongrie",
    "full_name": "University of Debrecen",
    "id": "grid.7122.6",
    "y": 2,
    "z": 38
  },
  {
    "name": "Rina Services (Italie)",
    "country": "Italie",
    "full_name": "Rina Services",
    "id": "grid.426062.4",
    "y": 2,
    "z": 159
  },
  {
    "name": "CNRS (France)",
    "country": "France",
    "full_name": "Centre national de la recherche scientifique",
    "acronym": "CNRS",
    "id": "n2X5f",
    "y": 2,
    "z": 2670
  },
  {
    "name": "Imec (Belgique)",
    "country": "Belgique",
    "full_name": "Imec",
    "id": "grid.15762.37",
    "y": 2,
    "z": 238
  },
  {
    "name": "Thales (France)",
    "country": "France",
    "full_name": "Thales",
    "acronym": "Thales",
    "id": "gent175",
    "y": 2,
    "z": 286
  },
  {
    "name": "Deloitte Conseil (France)",
    "country": "France",
    "full_name": "Deloitte Conseil",
    "acronym": "Deloitte Conseil",
    "id": "401948245",
    "y": 2,
    "z": 5
  },
  {
    "name": "Efficient Innovation (France)",
    "country": "France",
    "full_name": "Efficient Innovation",
    "acronym": "Efficient Innovation",
    "id": "417879509",
    "y": 2,
    "z": 10
  },
  {
    "name": "Fraunhofer Society (Allemagne)",
    "country": "Allemagne",
    "full_name": "Fraunhofer Society",
    "id": "grid.4561.6",
    "y": 2,
    "z": 1072
  },
  {
    "name": "Aarhus University (Danemark)",
    "country": "Danemark",
    "full_name": "Aarhus University",
    "id": "grid.7048.b",
    "y": 1,
    "z": 306
  },
  {
    "name": "Centro Ricerche Produzioni Animali (Italie)",
    "country": "Italie",
    "full_name": "Centro Ricerche Produzioni Animali",
    "id": "grid.423913.e",
    "y": 1,
    "z": 8
  },
  {
    "name": "West Pomeranian University of Technology (Pologne)",
    "country": "Pologne",
    "full_name": "West Pomeranian University of Technology",
    "id": "grid.411391.f",
    "y": 1,
    "z": 11
  },
  {
    "name": "Kiel University (Allemagne)",
    "country": "Allemagne",
    "full_name": "Kiel University",
    "id": "grid.9764.c",
    "y": 1,
    "z": 62
  },
  {
    "name": "Walloon Agricultural Research Centre (Belgique)",
    "country": "Belgique",
    "full_name": "Walloon Agricultural Research Centre",
    "id": "grid.22954.38",
    "y": 1,
    "z": 10
  },
  {
    "name": "University of Ljubljana (Slovénie)",
    "country": "Slovénie",
    "full_name": "University of Ljubljana",
    "id": "grid.8954.0",
    "y": 1,
    "z": 163
  },
  {
    "name": "Inagro (Belgique)",
    "country": "Belgique",
    "full_name": "Inagro",
    "id": "grid.434929.1",
    "y": 1,
    "z": 17
  },
  {
    "name": "CRA Hauts-de-France (France)",
    "country": "France",
    "full_name": "Chambre rég. d'agriculture des Hauts-de-France",
    "acronym": "CRA Hauts-de-France",
    "id": "130021678",
    "y": 1,
    "z": 1
  },
  {
    "name": "CRA Normandie (France)",
    "country": "France",
    "full_name": "Chambre rég. d'agriculture de Normandie",
    "acronym": "CRA Normandie",
    "id": "181400052",
    "y": 1,
    "z": 7
  },
  {
    "name": "Natural Resources Institute Finland (Finlande)",
    "country": "Finlande",
    "full_name": "Natural Resources Institute Finland",
    "id": "grid.22642.30",
    "y": 1,
    "z": 73
  },
  {
    "name": "CRA Bretagne Rennes (France)",
    "country": "France",
    "full_name": "Chambre rég. d'agriculture de Bretagne Rennes",
    "acronym": "CRA Bretagne Rennes",
    "id": "183500016",
    "y": 1,
    "z": 9
  },
  {
    "name": "Robopl@Net (France)",
    "country": "France",
    "full_name": "Robopl@Net",
    "acronym": "Robopl@Net",
    "id": "429364748",
    "y": 1,
    "z": 1
  },
  {
    "name": "CentraleSupélec (France)",
    "country": "France",
    "full_name": "CentraleSupélec",
    "acronym": "CentraleSupélec",
    "id": "m84Aa",
    "y": 1,
    "z": 60
  },
  {
    "name": "U. Lorraine (France)",
    "country": "France",
    "full_name": "Université de Lorraine",
    "acronym": "U. Lorraine",
    "id": "t6Cq5",
    "y": 1,
    "z": 69
  },
  {
    "name": "Trondheim Havn IKS (Norvège)",
    "country": "Norvège",
    "full_name": "Trondheim Havn IKS",
    "id": "grid.459106.f",
    "y": 1,
    "z": 2
  },
  {
    "name": "Norwegian University of Science and Technology (Norvège)",
    "country": "Norvège",
    "full_name": "Norwegian University of Science and Technology",
    "id": "grid.5947.f",
    "y": 1,
    "z": 199
  },
  {
    "name": "University of Trier (Allemagne)",
    "country": "Allemagne",
    "full_name": "University of Trier",
    "id": "grid.12391.38",
    "y": 1,
    "z": 17
  },
  {
    "name": "CETIM (France)",
    "country": "France",
    "full_name": "Centre technique des industries mécaniques",
    "acronym": "CETIM",
    "id": "TnAhv",
    "y": 1,
    "z": 10
  },
  {
    "name": "INSA de Lyon (France)",
    "country": "France",
    "full_name": "Institut national des sciences appliquées de Lyon",
    "acronym": "INSA de Lyon",
    "id": "8k41p",
    "y": 1,
    "z": 75
  },
  {
    "name": "Georgia Tech Lorraine (France)",
    "country": "France",
    "full_name": "Georgia Tech Lorraine",
    "acronym": "Georgia Tech Lorraine",
    "id": "OgYMq",
    "y": 1,
    "z": 5
  },
  {
    "name": "World Maritime University (Suède)",
    "country": "Suède",
    "full_name": "World Maritime University",
    "id": "grid.37472.35",
    "y": 1,
    "z": 6
  },
  {
    "name": "RWTH Aachen University (Allemagne)",
    "country": "Allemagne",
    "full_name": "RWTH Aachen University",
    "id": "grid.1957.a",
    "y": 1,
    "z": 251
  },
  {
    "name": "University of Klagenfurt (Autriche)",
    "country": "Autriche",
    "full_name": "University of Klagenfurt",
    "id": "grid.7520.0",
    "y": 1,
    "z": 21
  },
  {
    "name": "University of the Balearic Islands (Espagne)",
    "country": "Espagne",
    "full_name": "University of the Balearic Islands",
    "id": "grid.9563.9",
    "y": 1,
    "z": 19
  },
  {
    "name": "UBFC (France)",
    "country": "France",
    "full_name": "Université Bourgogne - Franche-Comté",
    "acronym": "UBFC",
    "id": "8A0mg",
    "y": 1,
    "z": 64
  },
  {
    "name": "UFC (France)",
    "country": "France",
    "full_name": "Université de Franche-Comté",
    "acronym": "UFC",
    "id": "7Mpgt",
    "y": 1,
    "z": 36
  },
  {
    "name": "Arts et Métiers (France)",
    "country": "France",
    "full_name": "Arts et Métiers Sciences et Technologies",
    "acronym": "Arts et Métiers",
    "id": "jYUcF",
    "y": 1,
    "z": 42
  },
  {
    "name": "Danaos (Chypre)",
    "country": "Chypre",
    "full_name": "Danaos",
    "id": "grid.423909.5",
    "y": 1,
    "z": 14
  },
  {
    "name": "University of Porto (Portugal)",
    "country": "Portugal",
    "full_name": "University of Porto",
    "id": "grid.5808.5",
    "y": 1,
    "z": 138
  },
  {
    "name": "Cetim Grand Est (France)",
    "country": "France",
    "full_name": "Cetim Grand Est",
    "acronym": "Cetim Grand Est",
    "id": "314257684",
    "y": 1,
    "z": 2
  },
  {
    "name": "X (France)",
    "country": "France",
    "full_name": "École polytechnique",
    "acronym": "X",
    "id": "DdW7n",
    "y": 1,
    "z": 85
  },
  {
    "name": "National Institute for Nuclear Physics (Italie)",
    "country": "Italie",
    "full_name": "National Institute for Nuclear Physics",
    "id": "grid.6045.7",
    "y": 1,
    "z": 119
  },
  {
    "name": "Smiths Detection France (France)",
    "country": "France",
    "full_name": "Smiths Detection France",
    "acronym": "Smiths Detection France",
    "id": "395262215",
    "y": 1,
    "z": 3
  },
  {
    "name": "Service Public Federal Finances (Belgique)",
    "country": "Belgique",
    "full_name": "Service Public Federal Finances",
    "id": "grid.438290.4",
    "y": 1,
    "z": 5
  },
  {
    "name": "University of Szeged (Hongrie)",
    "country": "Hongrie",
    "full_name": "University of Szeged",
    "id": "grid.9008.1",
    "y": 1,
    "z": 24
  },
  {
    "name": "Ludwig-Maximilians-Universität München (Allemagne)",
    "country": "Allemagne",
    "full_name": "Ludwig-Maximilians-Universität München",
    "id": "grid.5252.0",
    "y": 1,
    "z": 155
  },
  {
    "name": "ENSTA Paris (France)",
    "country": "France",
    "full_name": "École nationale supérieure de techniques avancées",
    "acronym": "ENSTA Paris",
    "id": "DY7kV",
    "y": 1,
    "z": 15
  },
  {
    "name": "Center for Physical Sciences and Technology (Lituanie)",
    "country": "Lituanie",
    "full_name": "Center for Physical Sciences and Technology",
    "id": "grid.425985.7",
    "y": 1,
    "z": 12
  }
]